{
  "type": "Feature",
  "properties": {
    "gn:admin1_code":"0.0",
    "gn:asciiname":"Jimkhar",
    "gn:country_code":"BT",
    "gn:dem":1931,
    "gn:feature_class":"P",
    "gn:feature_code":"PPL",
    "gn:name":"Jimkh\u0101r",
    "gn:population":0,
    "gn:timezone":"Asia/Thimphu",
    "iso:country":"BT",
    "wof:name":"Jimkhar",
    "wof:placetype":"locality"
},
  "geometry": {"coordinates":[91.50671,27.60687],"type":"Point"}
}