{
  "type": "Feature",
  "properties": {
    "gn:admin1_code":"0.0",
    "gn:asciiname":"Ngalangkang",
    "gn:cc2":"BT",
    "gn:country_code":"BT",
    "gn:dem":1203,
    "gn:feature_class":"P",
    "gn:feature_code":"PPL",
    "gn:name":"Ng\u0101langkang",
    "gn:population":0,
    "gn:timezone":"Asia/Thimphu",
    "iso:country":"BT",
    "name:und_x_variant":[
        "Khamna",
        "Khampa",
        "Ng\u0101langkang"
    ],
    "wof:name":"Ngalangkang",
    "wof:placetype":"locality"
},
  "geometry": {"coordinates":[91.58333,27.45],"type":"Point"}
}