{
  "type": "Feature",
  "properties": {
    "gn:admin1_code":"20.0",
    "gn:asciiname":"Lungtenzampa",
    "gn:country_code":"BT",
    "gn:dem":2319,
    "gn:feature_class":"P",
    "gn:feature_code":"PPLA",
    "gn:name":"Lungtenzampa",
    "gn:population":0,
    "gn:timezone":"Asia/Thimphu",
    "iso:country":"BT",
    "wof:name":"Lungtenzampa",
    "wof:placetype":"locality"
},
  "geometry": {"coordinates":[89.64440999999999,27.46821],"type":"Point"}
}