{
  "type": "Feature",
  "properties": {
    "gn:admin1_code":"10.0",
    "gn:asciiname":"Damthang",
    "gn:country_code":"BT",
    "gn:dem":2854,
    "gn:feature_class":"P",
    "gn:feature_code":"PPL",
    "gn:name":"Damthang",
    "gn:population":0,
    "gn:timezone":"Asia/Thimphu",
    "iso:country":"BT",
    "name:urd_x_preferred":[
        "\u062f\u0627\u0645\u062a\u06be\u0627\u0646\u06af"
    ],
    "wof:name":"Damthang",
    "wof:placetype":"locality"
},
  "geometry": {"coordinates":[89.34999999999999,27.41667],"type":"Point"}
}