{
  "type": "Feature",
  "properties": {
    "gn:admin1_code":"11.0",
    "gn:asciiname":"Khenpa Dzong",
    "gn:cc2":"BT",
    "gn:country_code":"BT",
    "gn:dem":1722,
    "gn:feature_class":"P",
    "gn:feature_code":"PPL",
    "gn:name":"Khenpa Dzong",
    "gn:population":0,
    "gn:timezone":"Asia/Thimphu",
    "iso:country":"BT",
    "name:und_x_variant":[
        "Thunkar",
        "Khenpa Dzong"
    ],
    "wof:name":"Khenpa Dzong",
    "wof:placetype":"locality"
},
  "geometry": {"coordinates":[91.08333,27.81667],"type":"Point"}
}