{
  "type": "Feature",
  "properties": {
    "iso:country":"BT",
    "name:ceb_x_preferred":[
        "Bhangtar"
    ],
    "name:dut_x_preferred":[
        "Bhangtar"
    ],
    "name:eng_x_preferred":[
        "Bhangtar"
    ],
    "name:swe_x_preferred":[
        "Bhangtar"
    ],
    "name:unk_x_variant":[
        "Bhangtar"
    ],
    "qs:gn_country":"BT",
    "qs:gn_fcode":"PPL",
    "qs:gn_pop":656,
    "qs:name":"Bhangamur",
    "qs:name_adm0":"India",
    "qs:name_adm1":"Assam",
    "qs:photos":0,
    "qs:photos_1k":0,
    "qs:photos_9k":0,
    "qs:photos_9r":0,
    "qs:photos_all":0,
    "qs:photos_sr":0,
    "qs:placetype":"Town",
    "qs:pop_sr":"2",
    "qs:woe_adm0":23424848,
    "wd:wordcount":48,
    "wof:name":"Bhangamur",
    "wof:placetype":"locality",
    "wof:population":656
},
  "geometry": {"coordinates":[91.71666999999999,26.81667],"type":"Point"}
}