{
  "type": "Feature",
  "properties": {
    "gn:country":"BT",
    "gn:fcode":"PPLA",
    "gn:population":872,
    "iso:country":"BT",
    "name:ast_x_preferred":[
        "Trashigang"
    ],
    "name:ben_x_preferred":[
        "\u099f\u09cd\u09b0\u09be\u09b6\u09bf\u0997\u09be\u0982"
    ],
    "name:ceb_x_preferred":[
        "Trashigang"
    ],
    "name:che_x_preferred":[
        "\u0422\u0440\u0430\u0448\u0438\u0433\u0430\u043d\u0433"
    ],
    "name:dan_x_preferred":[
        "Trashigang"
    ],
    "name:deu_x_preferred":[
        "Trashigang"
    ],
    "name:dzo_x_preferred":[
        "\u0f56\u0f40\u0fb2\u0f72\u0f66\u0f0b\u0f66\u0f92\u0f44\u0f0b"
    ],
    "name:eng_x_preferred":[
        "Tashigang"
    ],
    "name:eng_x_variant":[
        "Trashigang"
    ],
    "name:epo_x_preferred":[
        "Tra\u015digango"
    ],
    "name:est_x_preferred":[
        "Trashigang"
    ],
    "name:fas_x_preferred":[
        "\u062a\u0631\u0627\u0634\u06cc\u06af\u0627\u0646\u06af"
    ],
    "name:fra_x_preferred":[
        "Trashigang"
    ],
    "name:heb_x_preferred":[
        "\u05d8\u05e9\u05d9\u05d2\u05e0\u05d2"
    ],
    "name:ita_x_preferred":[
        "Trashigang"
    ],
    "name:jpn_x_preferred":[
        "\u30bf\u30b7\u30ac\u30f3"
    ],
    "name:kor_x_preferred":[
        "\ud2b8\ub77c\uc2dc\uac15"
    ],
    "name:lit_x_preferred":[
        "Tra\u0161igangas"
    ],
    "name:ltz_x_preferred":[
        "Trashigang"
    ],
    "name:nld_x_preferred":[
        "Trashigang"
    ],
    "name:pol_x_preferred":[
        "Trashigang"
    ],
    "name:por_x_preferred":[
        "Trashigang"
    ],
    "name:ron_x_preferred":[
        "Tashigang"
    ],
    "name:rus_x_preferred":[
        "\u0422\u0440\u0430\u0448\u0438\u0433\u0430\u043d\u0433"
    ],
    "name:spa_x_preferred":[
        "Trashigang"
    ],
    "name:swe_x_preferred":[
        "Trashigang"
    ],
    "name:tat_x_preferred":[
        "\u0422\u0440\u0430\u0448\u0438\u0433\u0430\u043d\u0433"
    ],
    "name:ukr_x_preferred":[
        "\u0422\u0440\u0430\u0448\u0456\u0433\u0430\u043d\u0433"
    ],
    "name:und_x_variant":[
        "Tashi Gang Dzong"
    ],
    "name:urd_x_preferred":[
        "\u062a\u0631\u0627\u0634\u06cc\u06af\u0627\u0646\u06af"
    ],
    "name:xmf_x_preferred":[
        "\u10e2\u10e0\u10d0\u10e8\u10d8\u10d2\u10d0\u10dc\u10d2\u10d8"
    ],
    "name:yue_x_preferred":[
        "\u624e\u897f\u5d17"
    ],
    "name:zho_x_preferred":[
        "\u5854\u5e0c\u5188"
    ],
    "qs:name":"Trashigang",
    "qs:photos_9r":0,
    "qs:photos_sr":0,
    "qs:pop_sr":"2",
    "wd:elevation":1174.0,
    "wd:wordcount":333,
    "wof:name":"Trashigang",
    "wof:placetype":"locality",
    "wof:population":872
},
  "geometry": {"coordinates":[91.55423999999999,27.3331],"type":"Point"}
}