{
  "type": "Feature",
  "properties": {
    "gn:admin1_code":"9.0",
    "gn:asciiname":"Sarpang",
    "gn:country_code":"BT",
    "gn:dem":344,
    "gn:feature_class":"P",
    "gn:feature_code":"PPLA",
    "gn:name":"Sarpang",
    "gn:population":10416,
    "gn:timezone":"Asia/Thimphu",
    "iso:country":"BT",
    "name:ceb_x_preferred":[
        "Sarpang"
    ],
    "name:deu_x_preferred":[
        "Sarpang"
    ],
    "name:epo_x_preferred":[
        "Sarpang"
    ],
    "name:est_x_preferred":[
        "Sarpang"
    ],
    "name:heb_x_preferred":[
        "\u05e9\u05e8\u05e4\u05e0\u05d2"
    ],
    "name:nld_x_preferred":[
        "Sarpang"
    ],
    "name:pol_x_preferred":[
        "Sarpang"
    ],
    "name:rus_x_preferred":[
        "\u0421\u0430\u0440\u043f\u0430\u043d\u0433"
    ],
    "name:ukr_x_preferred":[
        "\u0421\u0430\u0440\u043f\u0430\u043d\u0433"
    ],
    "name:und_x_variant":[
        "Sarbh\u0101ng"
    ],
    "wof:name":"Sarpang",
    "wof:placetype":"locality",
    "wof:population":10416
},
  "geometry": {"coordinates":[90.26745,26.86395],"type":"Point"}
}