{
  "type": "Feature",
  "properties": {
    "gn:admin1_code":"9.0",
    "gn:asciiname":"Sarpang",
    "gn:country_code":"BT",
    "gn:dem":344,
    "gn:feature_class":"P",
    "gn:feature_code":"PPLA",
    "gn:name":"Sarpang",
    "gn:population":10416,
    "gn:timezone":"Asia/Thimphu",
    "iso:country":"BT",
    "name:und_x_variant":[
        "Sarbh\u0101ng"
    ],
    "wof:name":"Sarpang",
    "wof:placetype":"locality",
    "wof:population":10416
},
  "geometry": {"coordinates":[90.26745,26.86395],"type":"Point"}
}