{
  "type": "Feature",
  "properties": {
    "gn:admin1_code":"18.0",
    "gn:asciiname":"Tingtibi",
    "gn:country_code":"BT",
    "gn:dem":551,
    "gn:feature_class":"P",
    "gn:feature_code":"PPL",
    "gn:name":"Tingtibi",
    "gn:population":0,
    "gn:timezone":"Asia/Thimphu",
    "iso:country":"BT",
    "wof:name":"Tingtibi",
    "wof:placetype":"locality"
},
  "geometry": {"coordinates":[90.68000000000001,27.15],"type":"Point"}
}