{
  "type": "Feature",
  "properties": {
    "gn:admin1_code":"0.0",
    "gn:asciiname":"Zarafi",
    "gn:country_code":"BT",
    "gn:dem":539,
    "gn:feature_class":"P",
    "gn:feature_code":"PPL",
    "gn:name":"Zar\u0101fi",
    "gn:population":0,
    "gn:timezone":"Asia/Thimphu",
    "iso:country":"BT",
    "wof:name":"Zarafi",
    "wof:placetype":"locality"
},
  "geometry": {"coordinates":[90.69223,27.14518],"type":"Point"}
}