{
  "type": "Feature",
  "properties": {
    "gn:admin1_code":"0.0",
    "gn:asciiname":"Usak",
    "gn:country_code":"BT",
    "gn:dem":3244,
    "gn:feature_class":"P",
    "gn:feature_code":"PPL",
    "gn:name":"Usak",
    "gn:population":0,
    "gn:timezone":"Asia/Thimphu",
    "iso:country":"BT",
    "name:heb_x_preferred":[
        "\u05d0\u05d5\u05e1\u05d0\u05e7"
    ],
    "wof:name":"Usak",
    "wof:placetype":"locality"
},
  "geometry": {"coordinates":[89.76667,27.25],"type":"Point"}
}