{
  "type": "Feature",
  "properties": {
    "gn:admin1_code":"0.0",
    "gn:asciiname":"Yalang",
    "gn:country_code":"BT",
    "gn:dem":2521,
    "gn:feature_class":"P",
    "gn:feature_code":"PPL",
    "gn:name":"Y\u0101lang",
    "gn:population":0,
    "gn:timezone":"Asia/Thimphu",
    "iso:country":"BT",
    "name:und_x_variant":[
        "Y\u0101lang"
    ],
    "name:urd_x_preferred":[
        "\u06cc\u0627\u0644\u0627\u0646\u06af"
    ],
    "wof:name":"Yalang",
    "wof:placetype":"locality"
},
  "geometry": {"coordinates":[91.63333,27.43333],"type":"Point"}
}