{
  "type": "Feature",
  "properties": {
    "gn:admin1_code":"0.0",
    "gn:asciiname":"Naspe",
    "gn:country_code":"BT",
    "gn:dem":3013,
    "gn:feature_class":"P",
    "gn:feature_code":"PPL",
    "gn:name":"Naspe",
    "gn:population":0,
    "gn:timezone":"Asia/Thimphu",
    "iso:country":"BT",
    "wof:name":"Naspe",
    "wof:placetype":"locality"
},
  "geometry": {"coordinates":[90.71666999999999,27.68333],"type":"Point"}
}