{
  "type": "Feature",
  "properties": {
    "gn:admin1_code":"0.0",
    "gn:asciiname":"Gamling",
    "gn:country_code":"BT",
    "gn:dem":2887,
    "gn:feature_class":"P",
    "gn:feature_code":"PPL",
    "gn:name":"G\u0101mling",
    "gn:population":0,
    "gn:timezone":"Asia/Thimphu",
    "iso:country":"BT",
    "name:cat_x_preferred":[
        "Gamling"
    ],
    "name:fra_x_preferred":[
        "Gamelin"
    ],
    "name:glg_x_preferred":[
        "Gamling"
    ],
    "name:ita_x_preferred":[
        "Gamling"
    ],
    "name:nld_x_preferred":[
        "Gamling"
    ],
    "name:pol_x_preferred":[
        "Lista Rohirrim\u00f3w#Gamling"
    ],
    "name:tur_x_preferred":[
        "Gamling"
    ],
    "name:zho_x_preferred":[
        "\u52a0\u59c6\u6797"
    ],
    "wof:name":"Gamling",
    "wof:placetype":"locality"
},
  "geometry": {"coordinates":[90.89183,27.62445],"type":"Point"}
}