{
  "type": "Feature",
  "properties": {
    "gn:admin1_code":"0.0",
    "gn:asciiname":"Tamjee",
    "gn:country_code":"BT",
    "gn:dem":1327,
    "gn:feature_class":"P",
    "gn:feature_code":"PPL",
    "gn:name":"Tamjee",
    "gn:population":0,
    "gn:timezone":"Asia/Thimphu",
    "iso:country":"BT",
    "wof:name":"Tamjee",
    "wof:placetype":"locality"
},
  "geometry": {"coordinates":[89.90000000000001,27.66667],"type":"Point"}
}