{
  "type": "Feature",
  "properties": {
    "gn:admin1_code":"0.0",
    "gn:asciiname":"Tosumani",
    "gn:country_code":"BT",
    "gn:dem":4081,
    "gn:feature_class":"P",
    "gn:feature_code":"PPL",
    "gn:name":"Tosumani",
    "gn:population":0,
    "gn:timezone":"Asia/Thimphu",
    "iso:country":"BT",
    "name:und_x_variant":[
        "Tosuman",
        "Tosumani"
    ],
    "wof:name":"Tosumani",
    "wof:placetype":"locality"
},
  "geometry": {"coordinates":[91.32035999999999,27.92727],"type":"Point"}
}