{
  "type": "Feature",
  "properties": {
    "gn:admin1_code":"0.0",
    "gn:asciiname":"Maogaon",
    "gn:country_code":"BT",
    "gn:dem":1192,
    "gn:feature_class":"P",
    "gn:feature_code":"PPL",
    "gn:name":"M\u0101ogaon",
    "gn:population":0,
    "gn:timezone":"Asia/Thimphu",
    "iso:country":"BT",
    "name:und_x_variant":[
        "M\u0101ogaon"
    ],
    "wof:name":"Maogaon",
    "wof:placetype":"locality"
},
  "geometry": {"coordinates":[90.40178,27.02587],"type":"Point"}
}