{
  "type": "Feature",
  "properties": {
    "gn:admin1_code":"0.0",
    "gn:asciiname":"Wangchukling",
    "gn:country_code":"BT",
    "gn:dem":2772,
    "gn:feature_class":"P",
    "gn:feature_code":"PPL",
    "gn:name":"Wangchukling",
    "gn:population":0,
    "gn:timezone":"Asia/Thimphu",
    "iso:country":"BT",
    "wof:name":"Wangchukling",
    "wof:placetype":"locality"
},
  "geometry": {"coordinates":[90.73333,27.55],"type":"Point"}
}