{
  "type": "Feature",
  "properties": {
    "gn:admin1_code":"17.0",
    "gn:asciiname":"Samdrup Jongkhar",
    "gn:country_code":"BT",
    "gn:dem":173,
    "gn:feature_class":"P",
    "gn:feature_code":"PPLA",
    "gn:name":"Samdrup Jongkhar",
    "gn:population":7507,
    "gn:timezone":"Asia/Thimphu",
    "iso:country":"BT",
    "wof:name":"Samdrup Jongkhar",
    "wof:placetype":"locality",
    "wof:population":7507
},
  "geometry": {"coordinates":[91.50519,26.80069],"type":"Point"}
}