{
  "type": "Feature",
  "properties": {
    "gn:admin1_code":"17.0",
    "gn:asciiname":"Samdrup Jongkhar",
    "gn:country_code":"BT",
    "gn:dem":173,
    "gn:feature_class":"P",
    "gn:feature_code":"PPLA",
    "gn:name":"Samdrup Jongkhar",
    "gn:population":7507,
    "gn:timezone":"Asia/Thimphu",
    "iso:country":"BT",
    "name:ceb_x_preferred":[
        "Samdrup Jongkhar"
    ],
    "name:dan_x_preferred":[
        "Samdrup Jongkhar"
    ],
    "name:dzo_x_preferred":[
        "\u0f56\u0f66\u0f58\u0f0b\u0f42\u0fb2\u0f74\u0f56\u0f0b\u0f63\u0f97\u0f7c\u0f44\u0f66\u0f0b\u0f58\u0f41\u0f62\u0f0b"
    ],
    "name:est_x_preferred":[
        "Samdrup Jongkhar"
    ],
    "name:fra_x_preferred":[
        "Samdrup Jongkhar"
    ],
    "name:ita_x_preferred":[
        "Samdrup Jongkhar"
    ],
    "name:lit_x_preferred":[
        "Samdrup D\u017eongkharas"
    ],
    "name:nld_x_preferred":[
        "Samdrup Jongkhar"
    ],
    "name:pol_x_preferred":[
        "Samdrup Jongkhar"
    ],
    "name:rus_x_preferred":[
        "\u0421\u0430\u043c\u0434\u0440\u0443\u043f-\u0414\u0436\u043e\u043d\u0433\u0445\u0430\u0440"
    ],
    "name:swe_x_preferred":[
        "Samdrup Jongkhar"
    ],
    "name:ukr_x_preferred":[
        "\u0421\u0430\u043c\u0434\u0440\u0443\u043f-\u0414\u0436\u043e\u043d\u0433\u0445\u0430\u0440"
    ],
    "name:urd_x_preferred":[
        "\u0633\u0627\u0645\u062f\u0631\u0648\u067e \u062c\u0648\u0646\u06af\u062e\u0627\u0631"
    ],
    "wof:name":"Samdrup Jongkhar",
    "wof:placetype":"locality",
    "wof:population":7507
},
  "geometry": {"coordinates":[91.50519,26.80069],"type":"Point"}
}