{
  "type": "Feature",
  "properties": {
    "gn:admin1_code":"0.0",
    "gn:asciiname":"Lobnig",
    "gn:country_code":"BT",
    "gn:dem":2412,
    "gn:feature_class":"P",
    "gn:feature_code":"PPL",
    "gn:name":"Lobnig",
    "gn:population":0,
    "gn:timezone":"Asia/Thimphu",
    "iso:country":"BT",
    "wof:name":"Lobnig",
    "wof:placetype":"locality"
},
  "geometry": {"coordinates":[89.55,27.15],"type":"Point"}
}