{
  "type": "Feature",
  "properties": {
    "gn:admin1_code":"17.0",
    "gn:asciiname":"Dewangiri",
    "gn:country_code":"BT",
    "gn:dem":559,
    "gn:feature_class":"P",
    "gn:feature_code":"PPL",
    "gn:name":"Dew\u0101ngiri",
    "gn:population":0,
    "gn:timezone":"Asia/Thimphu",
    "iso:country":"BT",
    "wof:name":"Dewangiri",
    "wof:placetype":"locality"
},
  "geometry": {"coordinates":[91.46666999999999,26.86667000000001],"type":"Point"}
}