{
  "type": "Feature",
  "properties": {
    "gn:admin1_code":"0.0",
    "gn:asciiname":"Kamganka",
    "gn:country_code":"BT",
    "gn:dem":1700,
    "gn:feature_class":"P",
    "gn:feature_code":"PPL",
    "gn:name":"Kamganka",
    "gn:population":0,
    "gn:timezone":"Asia/Thimphu",
    "iso:country":"BT",
    "wof:name":"Kamganka",
    "wof:placetype":"locality"
},
  "geometry": {"coordinates":[89.96068000000002,27.24981],"type":"Point"}
}