{
  "type": "Feature",
  "properties": {
    "gn:admin1_code":"0.0",
    "gn:asciiname":"Sana",
    "gn:country_code":"BT",
    "gn:dem":2714,
    "gn:feature_class":"P",
    "gn:feature_code":"PPL",
    "gn:name":"Sana",
    "gn:population":0,
    "gn:timezone":"Asia/Thimphu",
    "iso:country":"BT",
    "wof:name":"Sana",
    "wof:placetype":"locality"
},
  "geometry": {"coordinates":[91.38333,27.58333],"type":"Point"}
}